talisman_api/__init__.py
talisman_api/abstract.py
talisman_api/decorator.py
talisman_api/wrapper.py
talisman_api/api_client/__init__.py
talisman_api/api_client/client.py
talisman_api/api_client/composite.py
talisman_api/api_client/gql_clients/__init__.py
talisman_api/api_client/gql_clients/_abstract.py
talisman_api/api_client/gql_clients/_config.py
talisman_api/api_client/gql_clients/_keycloak.py
talisman_api/api_client/gql_clients/_noauth.py
talisman_api-1.4.1.data/data/VERSION
talisman_api-1.4.1.dist-info/METADATA
talisman_api-1.4.1.dist-info/WHEEL
talisman_api-1.4.1.dist-info/top_level.txt
talisman_api-1.4.1.dist-info/RECORD
